odoo10_addon_hr_period-10.0.1.2.0-nspkg.pth
odoo/addons/hr_period/README.rst
odoo/addons/hr_period/__init__.py
odoo/addons/hr_period/__manifest__.py
odoo/addons/hr_period/data/date_range_type.xml
odoo/addons/hr_period/data/ir_sequence_data.xml
odoo/addons/hr_period/i18n/de.po
odoo/addons/hr_period/i18n/es.po
odoo/addons/hr_period/i18n/fr.po
odoo/addons/hr_period/i18n/hr_period.pot
odoo/addons/hr_period/models/__init__.py
odoo/addons/hr_period/models/date_range_type.py
odoo/addons/hr_period/models/hr_contract.py
odoo/addons/hr_period/models/hr_employee.py
odoo/addons/hr_period/models/hr_fiscal_year.py
odoo/addons/hr_period/models/hr_payslip.py
odoo/addons/hr_period/models/hr_payslip_employees.py
odoo/addons/hr_period/models/hr_payslip_run.py
odoo/addons/hr_period/models/hr_period.py
odoo/addons/hr_period/security/hr_period_security.xml
odoo/addons/hr_period/security/ir.model.access.csv
odoo/addons/hr_period/static/description/icon.png
odoo/addons/hr_period/tests/__init__.py
odoo/addons/hr_period/tests/test_hr_fiscalyear.py
odoo/addons/hr_period/tests/test_payslip.py
odoo/addons/hr_period/views/date_range_type_view.xml
odoo/addons/hr_period/views/hr_fiscalyear_view.xml
odoo/addons/hr_period/views/hr_payslip_employee_view.xml
odoo/addons/hr_period/views/hr_payslip_run_view.xml
odoo/addons/hr_period/views/hr_payslip_view.xml
odoo/addons/hr_period/views/hr_period_view.xml
odoo10_addon_hr_period-10.0.1.2.0.dist-info/METADATA
odoo10_addon_hr_period-10.0.1.2.0.dist-info/WHEEL
odoo10_addon_hr_period-10.0.1.2.0.dist-info/namespace_packages.txt
odoo10_addon_hr_period-10.0.1.2.0.dist-info/top_level.txt
odoo10_addon_hr_period-10.0.1.2.0.dist-info/RECORD
